simple_gedcom/__init__.py
simple_gedcom/elements.py
simple_gedcom/gedcom_file.py
simple_gedcom/parser.py
simple_gedcom/pedigree.py
simple_gedcom/people.py
simple_gedcom/sources.py
simple_gedcom/utils.py
simple_gedcom-1.0.6.dist-info/LICENSE.txt
simple_gedcom-1.0.6.dist-info/METADATA
simple_gedcom-1.0.6.dist-info/WHEEL
simple_gedcom-1.0.6.dist-info/top_level.txt
simple_gedcom-1.0.6.dist-info/RECORD
