Metadata-Version: 2.1
Name: simple-gedcom
Version: 1.0.6
Summary: A Python module for reading and extracting data from GEDCOM files.
Home-page: https://github.com/mcobtechnology/simple-gedcom
Author: mcobtechnology
License: GPLv2
Keywords: python gedcom
Platform: UNKNOWN
Requires-Python: >=3.6
License-File: LICENSE.txt
Provides-Extra: test
Requires-Dist: pytest ; extra == 'test'
